P_KNN/P_KNN.py
P_KNN/P_KNN_CPU.py
P_KNN/P_KNN_GPU.py
P_KNN/P_KNN_config.py
P_KNN/P_KNN_memory_estimator.py
P_KNN/__init__.py
p_knn-1.0.0.dist-info/licenses/LICENSE
p_knn-1.0.0.dist-info/METADATA
p_knn-1.0.0.dist-info/WHEEL
p_knn-1.0.0.dist-info/entry_points.txt
p_knn-1.0.0.dist-info/top_level.txt
p_knn-1.0.0.dist-info/RECORD
