Metadata-Version: 2.4
Name: P_KNN
Version: 1.0.0
Summary: P-KNN command line tool
Author: Po-Yu Lin, Nadav Brandes
Requires-Python: >=3.8
License-File: LICENSE
Requires-Dist: numpy
Requires-Dist: pandas
Requires-Dist: scikit-learn
Requires-Dist: tqdm
Requires-Dist: huggingface_hub
Provides-Extra: gpu
Requires-Dist: torch; extra == "gpu"
Provides-Extra: cpu
Requires-Dist: joblib; extra == "cpu"
Provides-Extra: all
Requires-Dist: torch; extra == "all"
Requires-Dist: joblib; extra == "all"
Dynamic: license-file
